ped/__init__.py
ped/guess_module.py
ped/install_completion.py
ped/ped_bash_completion.sh
ped/ped_zsh_completion.zsh
ped/py.typed
ped/pypath.py
ped/style.py
ped-3.0.0.dist-info/entry_points.txt
ped-3.0.0.dist-info/LICENSE
ped-3.0.0.dist-info/WHEEL
ped-3.0.0.dist-info/METADATA
ped-3.0.0.dist-info/RECORD
