Metadata-Version: 2.1
Name: ped
Version: 3.0.0
Summary: Quickly open Python modules in your text editor.
Keywords: commandline,cli,open,editor,editing
Author-email: Steven Loria <sloria1@gmail.com>
Requires-Python: >=3.8
Classifier: Intended Audience :: Developers
Classifier: License :: OSI Approved :: MIT License
Classifier: Natural Language :: English
Classifier: Programming Language :: Python :: 3
Classifier: Programming Language :: Python :: 3.8
Classifier: Programming Language :: Python :: 3.9
Classifier: Programming Language :: Python :: 3.10
Classifier: Programming Language :: Python :: 3.11
Classifier: Programming Language :: Python :: 3.12
Classifier: Topic :: System :: Shells
Requires-Dist: ped[tests] ; extra == "dev"
Requires-Dist: tox ; extra == "dev"
Requires-Dist: pytest ; extra == "tests"
Requires-Dist: pytest-mock ; extra == "tests"
Requires-Dist: scripttest==1.3 ; extra == "tests"
Project-URL: Issues, https://github.com/sloria/ped/issues
Project-URL: Source, https://github.com/sloria/ped/
Provides-Extra: dev
Provides-Extra: tests
